{
  "disease": {
    "id": "acute_fatty_liver_of_pregnancy",
    "name": "Acute Fatty Liver of Pregnancy (AFLP)",
    "system": "obstetrics",
    "department": "obstetrics",
    "unit": "high-risk-pregnancy",
    "agePeak_months": [264, 360],
    "note": "Life-threatening obstetric emergency characterized by microvesicular fatty infiltration of hepatocytes in third trimester. Incidence 1:7,000-15,000 pregnancies. Caused by mitochondrial fatty acid oxidation defects (LCHAD deficiency) in the fetus, with maternal hepatotoxicity from accumulated metabolites. High maternal mortality (10-15%) and perinatal mortality (15-25%). Early recognition and prompt delivery are essential.",
    "prevalenceWeight": 0.05,
    "syndromeTags": ["pregnancy", "liver_failure", "obstetric_emergency", "fatty_liver", "mitochondrial"],

    "severityAssessment": {
      "immediateDangerSigns": [
        { "sign": "acute_liver_failure_coagulopathy_encephalopathy", "weight": 10 },
        { "sign": "hepatic_encephalopathy_any_grade", "weight": 10 },
        { "sign": "severe_hypoglycemia_glucose_less_than_3", "weight": 9 },
        { "sign": "disseminated_intravascular_coagulation", "weight": 9 },
        { "sign": "acute_renal_failure", "weight": 8 },
        { "sign": "multiorgan_failure", "weight": 10 },
        { "sign": "maternal_consciousness_level_decreased", "weight": 9 }
      ],
      "severeCriteria": {
        "anyDangerSign": true,
        "acog_clinical_diagnosis_3_features": true,
        "swansea_criteria_6_or_more": true
      },
      "nonSevereCriteria": {
        "noDangerSigns": true,
        "early_mild_disease": true,
        "swansea_criteria_less_than_6": true
      },
      "severityLabel": "Suspected AFLP -> EMERGENCY delivery; Fulminant/encephalopathy -> ICU + transplant center; Early/mild -> EXPEDITE delivery after steroids if <34w"
    },

    "presentingComplaints": [
      "Nausea and vomiting (often the first symptom)",
      "Right upper abdominal or epigastric pain",
      "Malaise and profound fatigue",
      "Yellowing of the skin and eyes",
      "Mental confusion or drowsiness",
      "Excessive thirst"
    ],

    "historyFeatures": [
      { "symptomId": "nausea_vomiting_persistent", "weight": 5, "note": "Often the first symptom; severe and persistent" },
      { "symptomId": "right_upper_quadrant_epigastric_pain", "weight": 4 },
      { "symptomId": "fatigue_malaise", "weight": 4 },
      { "symptomId": "jaundice", "weight": 4, "note": "Develops days after initial symptoms" },
      { "symptomId": "appetite_changes", "weight": 3 },
      { "symptomId": "headache", "weight": 2 },
      { "symptomId": "polydipsia_excessive_thirst", "weight": 3, "note": "Due to diabetes insipidus-like state from vasopressinase" },
      { "symptomId": "pruritus", "weight": 2 },
      { "symptomId": "confusion_altered_mental_status", "weight": 4, "note": "Hepatic encephalopathy" },
      { "symptomId": "dark_urine", "weight": 2 },
      { "symptomId": "oliguria", "weight": 2 },
      { "symptomId": "symptoms_of_preeclampsia", "weight": 2, "note": "May coexist in 50%; hypertension, proteinuria" },
      { "symptomId": "first_pregnancy_or_previous_aflp", "weight": 3 },
      { "symptomId": "multiple_gestation", "weight": 2 },
      { "symptomId": "male_fetus_known", "weight": 2, "note": "Associated with LCHAD deficiency in male fetus" }
    ],

    "examFeatures": [
      { "signId": "jaundice_scleral_icterus", "baseWeight": 5 },
      { "signId": "right_upper_quadrant_tenderness", "baseWeight": 4 },
      { "signId": "hepatomegaly", "baseWeight": 2, "note": "Liver may be small/normal in late stage" },
      { "signId": "ascites", "baseWeight": 2 },
      { "signId": "fever", "baseWeight": 2 },
      { "signId": "tachycardia", "baseWeight": 2 },
      { "signId": "hypertension", "baseWeight": 2, "note": "Present in 50%; may be absent" },
      { "signId": "peripheral_edema", "baseWeight": 2 },
      { "signId": "confusion_or_somnolence", "baseWeight": 3, "note": "Encephalopathy" },
      { "signId": "signs_of_bleeding_petechiae_bruising", "baseWeight": 2, "note": "Coagulopathy" },
      { "signId": "asterixis", "baseWeight": 3, "note": "Encephalopathy" }
    ],

    "riskFactors": [
      { "id": "first_pregnancy_primigravida", "multiplier": 3.0 },
      { "id": "multiple_gestation", "multiplier": 3.0 },
      { "id": "male_fetus", "multiplier": 2.0 },
      { "id": "previous_aflp_in_prior_pregnancy", "multiplier": 5.0 },
      { "id": "fetal_lchad_deficiency_long_chain_3_hydroxyacyl_coa_dehydrogenase", "multiplier": 10.0 },
      { "id": "maternal_lchad_mutation_heterozygote", "multiplier": 5.0 },
      { "id": "preeclampsia", "multiplier": 2.0 },
      { "id": "low_bmi_underweight", "multiplier": 1.5 },
      { "id": "third_trimester_28_40_weeks", "multiplier": 3.0 }
    ],

    "mimics": [
      {
        "diseaseId": "hellp_syndrome",
        "discriminators": ["hypertension_more_pronounced", "severe_thrombocytopenia_typical", "schistocytes_on_film", "microangiopathic_hemolysis", "normal_glucose_or_elevated"]
      },
      {
        "diseaseId": "acute_viral_hepatitis_hav_hbv_hev",
        "discriminators": ["positive_viral_serology", "marked_transaminitis_alt_ast_1000_or_higher", "no_hypoglycemia", "no_leukocytosis_or_polymorphs"]
      },
      {
        "diseaseId": "drug_induced_liver_injury_in_pregnancy",
        "discriminators": ["temporal_relation_to_drug", "no_polydipsia", "no_gastrointestinal_prodrome"]
      },
      {
        "diseaseId": "intrahepatic_cholestasis_of_pregnancy",
        "discriminators": ["pruritus_predominant_symptom", "elevated_bile_acids", "normal_glucose", "no_coagulopathy", "no_encephalopathy"]
      },
      {
        "diseaseId": "sepsis_associated_liver_dysfunction",
        "discriminators": ["source_of_infection_identified", "fever_rigors_predominant", "leukocytosis_or_left_shift", "blood_culture_positive"]
      }
    ],

    "investigations": {
      "bedside": [
        { "name": "Blood glucose by glucometer", "priority": "immediate", "yield": 0.8, "indication": "hypoglycemia is a hallmark of AFLP; frequent monitoring required" },
        { "name": "Urine dipstick", "priority": "high", "yield": 0.5, "indication": "bilirubinuria; proteinuria may be present" }
      ],
      "laboratory": [
        { "name": "LFTs (ALT, AST, ALP, GGT, total and direct bilirubin)", "priority": "immediate", "yield": 0.9, "indication": "elevated transaminases (typically 300-1000, moderate elevation), elevated bilirubin (mixed), elevated ALP" },
        { "name": "FBC with platelets", "priority": "immediate", "yield": 0.8, "indication": "thrombocytopenia (mild-moderate); less severe than HELLP; leukocytosis common" },
        { "name": "INR/PT/PTT", "priority": "immediate", "yield": 0.9, "indication": "prolonged PT/INR due to synthetic dysfunction and DIC" },
        { "name": "Serum glucose", "priority": "immediate", "yield": 0.85, "indication": "hypoglycemia is characteristic; from impaired gluconeogenesis and glycogen depletion" },
        { "name": "Serum creatinine and urea", "priority": "high", "yield": 0.7, "indication": "elevated in acute kidney injury" },
        { "name": "Uric acid", "priority": "high", "yield": 0.7, "indication": "markedly elevated early in AFLP; helps distinguish from HELLP" },
        { "name": "Serum ammonia", "priority": "high", "yield": 0.6, "indication": "elevated in acute liver failure/encephalopathy" },
        { "name": "LDH", "priority": "high", "yield": 0.5, "indication": "mildly elevated; less than in HELLP" },
        { "name": "Haptoglobin", "priority": "medium", "yield": 0.3, "indication": "may be normal or slightly decreased" },
        { "name": "Fibrinogen and D-dimer", "priority": "high", "yield": 0.7, "indication": "low fibrinogen + elevated D-dimer = DIC" },
        { "name": "Blood gas (arterial or venous)", "priority": "high", "yield": 0.6, "indication": "metabolic acidosis suggests multiorgan failure" },
        { "name": "Swansea Criteria for AFLP diagnosis", "priority": "high", "yield": 0.95, "indication": "6 or more of: vomiting, abdominal pain, polydipsia, bilirubin >14, hypoglycemia <4, urate >340, WCC >11, elevated transaminases, elevated NH3, renal impairment, coagulopathy, microvesicular steatosis, ascites/bright liver on US" }
      ],
      "imaging": [
        { "name": "Abdominal ultrasound", "priority": "high", "yield": 0.6, "indication": "bright/hyperechoic liver (fatty infiltration); may appear normal in early disease; ascites; excludes gallstones" },
        { "name": "Obstetric ultrasound with fetal assessment", "priority": "high", "yield": 0.4, "indication": "fetal well-being; biophysical profile" },
        { "name": "CT abdomen (non-contrast)", "priority": "medium", "yield": 0.7, "indication": "liver hypodensity compared to spleen (fatty infiltration); use only if diagnosis uncertain" },
        { "name": "Liver biopsy", "priority": "selected", "yield": 0.98, "indication": "gold standard: microvesicular steatosis (foamy hepatocytes with central nucleus); rarely performed clinically (risk of bleeding); diagnosis usually clinical using Swansea criteria" }
      ]
    },

    "management": {
      "protocolReference": "ACOG Practice Bulletin: Liver Disease in Pregnancy; SHEA Guideline: Acute Fatty Liver of Pregnancy; Swansea Criteria",
      "pathways": [
        {
          "severity": "suspected_aflp_any_gestational_age",
          "criteria": "Third trimester (usually >30w) with nausea/vomiting, RUQ pain, jaundice, + Swansea criteria >=6; or high clinical suspicion",
          "treatment": "URGENT admission to ICU/HDU. Multidisciplinary team: obstetrics, hepatology, maternal-fetal medicine, critical care, anesthesia, neonatology. Stabilize: correct hypoglycemia (IV dextrose 10-50% as needed), correct coagulopathy (vitamin K 10mg IV, FFP if actively bleeding or INR >2 prior to delivery), IV fluids, N-acetylcysteine (NAC 150mg/kg IV load then maintenance — may benefit hepatic recovery). Evaluate for delivery: AFLP is an obstetric emergency; prompt delivery is the definitive treatment."
        },
        {
          "severity": "delivery_planning",
          "criteria": "Confirmed AFLP at any gestational age after stabilization",
          "treatment": "DELIVER within 24-48h of diagnosis, often within hours if severe. If <34w: give betamethasone 12mg IM q24h x 2 doses only if delivery can be delayed 24-48h; do NOT delay if maternal instability. Mode: vaginal delivery preferred if cervix favorable and no fetal distress (induction of labor). Cesarean if unfavorable cervix, fetal distress, or maternal deterioration. Avoid general anesthesia (hepatotoxic agents, risk of worsening liver failure). Regional anesthesia if platelets >50,000 and no coagulopathy. Meticulous hemostasis. Prepare for postpartum hemorrhage."
        },
        {
          "severity": "postpartum_care",
          "criteria": "After delivery of baby and placenta",
          "treatment": "Continue ICU monitoring for 48-72h (AFLP may worsen before improving). Correct hypoglycemia aggressively. Monitor LFTs, INR, glucose, renal function q6h. NAC IV 3-day protocol. Manage DIC with component therapy (platelets, FFP, cryoprecipitate). Renal replacement therapy if AKI persists. Most patients improve within 48-72h; if not improving, consider liver transplant evaluation. Counsel: AFLP recurs in 10-20% of subsequent pregnancies. Test mother and baby for LCHAD deficiency (genetic testing). Baby: monitor for hypoglycemia, LCHAD deficiency symptoms; dietary management (MCT oil)."
        },
        {
          "severity": "acute_liver_failure_transplant_evaluation",
          "criteria": "Progressive deterioration despite delivery: worsening encephalopathy, INR >4, hypoglycemia refractory, multiorgan failure",
          "treatment": "Transplant center consultation. King's College Criteria for transplant in AFLP. Bridging: MARS (albumin dialysis), plasmapheresis, continuous RRT. Most AFLP patients recover with time and supportive care; transplant rarely needed (<5%). If transplant: maternal outcomes are good. Long-term recovery is typically complete in survivors."
        }
      ]
    },

    "pathophysiology": [
      "fetal_lchad_deficiency_long_chain_3_hydroxyacyl_coa_dehydrogenase",
      "accumulation_of_fatty_acid_metabolites_in_fetal_placental_unit",
      "transfer_to_maternal_circulation",
      "mitochondrial_toxicity_in_maternal_hepatocytes",
      "microvesicular_fatty_infiltration_of_hepatocytes",
      "impaired_mitochondrial_beta_oxidation",
      "hepatocellular_dysfunction_and_necrosis",
      "impaired_gluconeogenesis_causing_hypoglycemia",
      "impaired_urea_synthesis_causing_hyperammonemia",
      "impaired_coagulation_factor_synthesis",
      "acute_kidney_injury_from_multifactorial_causes",
      "progression_to_fulminant_liver_failure",
      "reversal_after_delivery_in_most_cases"
    ],

    "complications": [
      {
        "diseaseId": "acute_liver_failure",
        "probability": 0.2,
        "severityBoost": 1.0,
        "clues": ["hypoglycemia", "coagulopathy", "encephalopathy", "progressive_hyperbilirubinemia"]
      },
      {
        "diseaseId": "disseminated_intravascular_coagulation_dic",
        "probability": 0.3,
        "severityBoost": 0.6,
        "clues": ["prolonged_pt_ptt", "low_fibrinogen", "elevated_d_dimer", "thrombocytopenia", "active_bleeding"]
      },
      {
        "diseaseId": "acute_kidney_injury_renal_failure",
        "probability": 0.4,
        "severityBoost": 0.5,
        "clues": ["oliguria_anuria", "rising_creatinine", "metabolic_acidosis", "hyperkalemia"]
      },
      {
        "diseaseId": "severe_hypoglycemia",
        "probability": 0.6,
        "severityBoost": 0.5,
        "clues": ["serum_glucose_less_than_3_mmol_l", "altered_consciousness", "requires_dextrose_infusion"]
      },
      {
        "diseaseId": "postpartum_hemorrhage",
        "probability": 0.3,
        "severityBoost": 0.5,
        "clues": ["coagulopathy", "uterine_atony", "traumatic_delivery", "estimated_blood_loss_greater_than_1000ml"]
      },
      {
        "diseaseId": "pancreatitis",
        "probability": 0.1,
        "severityBoost": 0.4,
        "clues": ["epigastric_pain", "elevated_amylase_lipase", "nausea_vomiting"]
      },
      {
        "diseaseId": "maternal_death",
        "probability": 0.1,
        "severityBoost": 1.0,
        "clues": ["multiorgan_failure", "fulminant_liver_failure", "sepsis", "cerebral_edema"]
      },
      {
        "diseaseId": "intrauterine_fetal_death",
        "probability": 0.15,
        "severityBoost": 0.8,
        "clues": ["absent_fetal_movements", "fetal_distress_non_reassuring_fetal_heart_rate", "maternal_deterioration"]
      }
    ],

    "mustNotMiss": true,
    "emergencyPriority": "high",
    "diagnosticClues": ["third_trimester_nausea_vomiting_ruq_pain", "jaundice", "hypoglycemia", "elevated_uric_acid", "coagulopathy", "swansea_criteria_6_or_more"],
    "exclusionClues": ["no_pregnancy", "early_gestation_first_second_trimester", "normal_glucose_and_uric_acid", "negative_swansea_criteria"]
  }
}
